DEVELOPMENT.rst
MANIFEST.in
Makefile
README.rst
setup.py
Tango.egg-info/PKG-INFO
Tango.egg-info/SOURCES.txt
Tango.egg-info/dependency_links.txt
Tango.egg-info/entry_points.txt
Tango.egg-info/not-zip-safe
Tango.egg-info/requires.txt
Tango.egg-info/top_level.txt
examples/gists.py
talks/introduction/introducing-tango.rst
tango/__init__.py
tango/app.py
tango/config.py
tango/errors.py
tango/filters.py
tango/imports.py
tango/manage.py
tango/shelf.py
tango/writers.py
tango/factory/__init__.py
tango/factory/app.py
tango/factory/context.py
tango/factory/snapshot.py
tango/factory/stash.py
tango/tools/__init__.py
tango/tools/scraper.py
tango/tools/twitter.py
tests/common_tests.py
tests/common_tests.pyc
tests/csv.csv
tests/empty.py
tests/empty.pyc
tests/exclude.txt
tests/manyroutes.py
tests/manyroutes.pyc
tests/sampletypes.py
tests/sampletypes.pyc
tests/shelf.dat
tests/simple.html
tests/simplest.py
tests/simplest.pyc
tests/test_app_init.py
tests/test_app_init.pyc
tests/test_command_line.rst
tests/test_config_context.rst
tests/test_filters.py
tests/test_flask.py
tests/test_hybrid_app.rst
tests/test_nosuchwriter.py
tests/test_route_serialization.py
tests/test_shelf_base_connector.py
tests/test_shelf_sqlite_connector.py
tests/test_single_module_app.py
tests/test_view_args.rst
tests/test_warnings.py
tests/errors/dummy.py
tests/errors/importerror.py
tests/errors/indexerror.py
tests/errors/nosuchwriter.py
tests/errors/errorsite/__init__.py
tests/errors/errorsite/__init__.pyc
tests/errors/errorsite/stash/__init__.py
tests/errors/errorsite/stash/__init__.pyc
tests/errors/errorsite/stash/hybrid.py
tests/errors/errorsite/stash/importerror/__init__.py
tests/errors/errorsite/stash/importerror/__init__.pyc
tests/errors/errorsite/stash/importerror/exists.py
tests/hybrid/__init__.py
tests/hybrid/__init__.pyc
tests/hybrid/stash.py
tests/hybrid/stash.pyc
tests/newtest/__init__.py
tests/newtest/__init__.pyc
tests/newtest/index.py
tests/newtest/index.pyc
tests/newtest/sample.py
tests/newtest/sample.pyc
tests/simplesite/__init__.py
tests/simplesite/__init__.pyc
tests/simplesite/config.py
tests/simplesite/config.pyc
tests/simplesite/stash/__init__.py
tests/simplesite/stash/__init__.pyc
