Metadata-Version: 1.0
Name: Tango
Version: 0.2.7
Summary: Tango mobile web optimization framework.
Home-page: http://www.willowtreeapps.com
Author: WillowTree Apps DevOps Team
Author-email: devops@willowtreeapps.com
License: BSD
Platform: POSIX
